mortgage/__init__.py
mortgage/loan.py
mortgage-1.0.5.dist-info/LICENSE
mortgage-1.0.5.dist-info/METADATA
mortgage-1.0.5.dist-info/WHEEL
mortgage-1.0.5.dist-info/top_level.txt
mortgage-1.0.5.dist-info/RECORD
