Metadata-Version: 2.1
Name: mortgage
Version: 1.0.5
Summary: Mortgage Calculator
Home-page: https://github.com/austinmcconnell/mortgage
Author: Austin McConnell
Author-email: austin.s.mcconnell@gmail.com
License: MIT license
Keywords: mortgage
Platform: UNKNOWN
Classifier: Development Status :: 5 - Production/Stable
Classifier: Intended Audience :: Developers
Classifier: License :: OSI Approved :: MIT License
Classifier: Natural Language :: English
Classifier: Programming Language :: Python :: 3
Classifier: Programming Language :: Python :: 3.5
Classifier: Programming Language :: Python :: 3.6
Classifier: Programming Language :: Python :: 3.7
Requires-Python: >=3.5
Provides-Extra: develop
